quantor/__init__.py
quantor/activations.py
quantor/activations_tf.py
quantor/audio_utils.py
quantor/cache_utils.py
quantor/configuration_utils.py
quantor/convert_graph_to_onnx.py
quantor/convert_pytorch_checkpoint_to_tf2.py
quantor/convert_slow_tokenizer.py
quantor/convert_slow_tokenizers_checkpoints_to_fast.py
quantor/convert_tf_hub_seq_to_seq_bert_to_pytorch.py
quantor/debug_utils.py
quantor/dependency_versions_check.py
quantor/dependency_versions_table.py
quantor/dynamic_module_utils.py
quantor/feature_extraction_sequence_utils.py
quantor/feature_extraction_utils.py
quantor/file_utils.py
quantor/hf_argparser.py
quantor/hyperparameter_search.py
quantor/image_processing_base.py
quantor/image_processing_utils.py
quantor/image_processing_utils_fast.py
quantor/image_transforms.py
quantor/image_utils.py
quantor/keras_callbacks.py
quantor/modelcard.py
quantor/modeling_attn_mask_utils.py
quantor/modeling_flash_attention_utils.py
quantor/modeling_flax_outputs.py
quantor/modeling_flax_pytorch_utils.py
quantor/modeling_flax_utils.py
quantor/modeling_gguf_pytorch_utils.py
quantor/modeling_outputs.py
quantor/modeling_rope_utils.py
quantor/modeling_tf_outputs.py
quantor/modeling_tf_pytorch_utils.py
quantor/modeling_tf_utils.py
quantor/modeling_utils.py
quantor/optimization.py
quantor/optimization_tf.py
quantor/processing_utils.py
quantor/pytorch_utils.py
quantor/safetensors_conversion.py
quantor/testing_utils.py
quantor/tf_utils.py
quantor/time_series_utils.py
quantor/tokenization_utils.py
quantor/tokenization_utils_base.py
quantor/tokenization_utils_fast.py
quantor/trainer.py
quantor/trainer_callback.py
quantor/trainer_pt_utils.py
quantor/trainer_seq2seq.py
quantor/trainer_utils.py
quantor/training_args.py
quantor/training_args_seq2seq.py
quantor/training_args_tf.py
quantor/agents/__init__.py
quantor/agents/agent_types.py
quantor/agents/agents.py
quantor/agents/default_tools.py
quantor/agents/document_question_answering.py
quantor/agents/evaluate_agent.py
quantor-0.0.4.dist-info/LICENSE
quantor-0.0.4.dist-info/WHEEL
quantor-0.0.4.dist-info/METADATA
quantor-0.0.4.dist-info/RECORD
